ker/__init__.py
ker/main.py
ker/api/__init__.py
ker/api/account.py
ker/api/dns.py
ker/api/list.py
ker/api/monitor.py
ker/api/server.py
ker/api/ssh.py
ker/utils/__init__.py
ker/utils/request.py
ker.py-0.0.2.dist-info/LICENSE
ker.py-0.0.2.dist-info/METADATA
ker.py-0.0.2.dist-info/WHEEL
ker.py-0.0.2.dist-info/top_level.txt
ker.py-0.0.2.dist-info/RECORD
