Metadata-Version: 2.1
Name: ker.py
Version: 0.0.2
Summary: Hostker Python SDK
Home-page: UNKNOWN
Author: SkyAo
Author-email: csvwolf@qq.com
License: UNKNOWN
Platform: UNKNOWN
